ukis_csmask/__init__.py
ukis_csmask/mask.py
ukis_csmask/model_4b_l1c.json
ukis_csmask/model_4b_l1c.onnx
ukis_csmask/model_4b_l2a.json
ukis_csmask/model_4b_l2a.onnx
ukis_csmask/model_6b_l1c.json
ukis_csmask/model_6b_l1c.onnx
ukis_csmask/model_6b_l2a.json
ukis_csmask/model_6b_l2a.onnx
ukis_csmask/utils.py
ukis_csmask-1.0.0.dist-info/licenses/LICENSE
ukis_csmask-1.0.0.dist-info/METADATA
ukis_csmask-1.0.0.dist-info/WHEEL
ukis_csmask-1.0.0.dist-info/top_level.txt
ukis_csmask-1.0.0.dist-info/RECORD
