Metadata-Version: 2.4
Name: ukis-csmask
Version: 1.0.0
Summary: masks clouds and cloud shadows in Sentinel-2, Landsat-8, Landsat-7 and Landsat-5 images
Home-page: https://github.com/dlr-eoc/ukis-csmask
Author: German Aerospace Center (DLR)
Author-email: ukis-helpdesk@dlr.de
License: Apache 2.0
Classifier: Programming Language :: Python :: 3
Classifier: Operating System :: OS Independent
Classifier: Development Status :: 4 - Beta
Classifier: License :: OSI Approved :: Apache Software License
Classifier: Topic :: Scientific/Engineering :: GIS
Requires-Python: >=3.8
License-File: LICENSE
Requires-Dist: numpy
Requires-Dist: scipy
Provides-Extra: cpu
Requires-Dist: onnxruntime; extra == "cpu"
Provides-Extra: gpu
Requires-Dist: onnxruntime-gpu; extra == "gpu"
Provides-Extra: openvino
Requires-Dist: onnxruntime-openvino; extra == "openvino"
Provides-Extra: dev
Requires-Dist: pytest; extra == "dev"
Dynamic: author
Dynamic: author-email
Dynamic: classifier
Dynamic: description
Dynamic: description-content-type
Dynamic: home-page
Dynamic: license
Dynamic: license-file
Dynamic: provides-extra
Dynamic: requires-dist
Dynamic: requires-python
Dynamic: summary
